odoo/addons/l10n_ch_base_bank/README.rst
odoo/addons/l10n_ch_base_bank/__init__.py
odoo/addons/l10n_ch_base_bank/__manifest__.py
odoo/addons/l10n_ch_base_bank/postfinance.py
odoo/addons/l10n_ch_base_bank/i18n/de.po
odoo/addons/l10n_ch_base_bank/i18n/fr.po
odoo/addons/l10n_ch_base_bank/i18n/it.po
odoo/addons/l10n_ch_base_bank/i18n/l10n_ch_base_bank.pot
odoo/addons/l10n_ch_base_bank/models/__init__.py
odoo/addons/l10n_ch_base_bank/models/bank.py
odoo/addons/l10n_ch_base_bank/models/invoice.py
odoo/addons/l10n_ch_base_bank/models/partner_bank.py
odoo/addons/l10n_ch_base_bank/readme/CONTRIBUTORS.rst
odoo/addons/l10n_ch_base_bank/readme/CREDITS.rst
odoo/addons/l10n_ch_base_bank/readme/DESCRIPTION.rst
odoo/addons/l10n_ch_base_bank/readme/USAGE.rst
odoo/addons/l10n_ch_base_bank/static/description/icon.png
odoo/addons/l10n_ch_base_bank/static/description/index.html
odoo/addons/l10n_ch_base_bank/tests/__init__.py
odoo/addons/l10n_ch_base_bank/tests/test_bank.py
odoo/addons/l10n_ch_base_bank/tests/test_bank_type.py
odoo/addons/l10n_ch_base_bank/tests/test_create_invoice.py
odoo/addons/l10n_ch_base_bank/tests/test_search_invoice.py
odoo/addons/l10n_ch_base_bank/views/bank.xml
odoo13_addon_l10n_ch_base_bank-13.0.1.0.1.dev20.dist-info/METADATA
odoo13_addon_l10n_ch_base_bank-13.0.1.0.1.dev20.dist-info/WHEEL
odoo13_addon_l10n_ch_base_bank-13.0.1.0.1.dev20.dist-info/top_level.txt
odoo13_addon_l10n_ch_base_bank-13.0.1.0.1.dev20.dist-info/RECORD
